spython/README.md
spython/__init__.py
spython/image.py
spython/version.py
spython/client/__init__.py
spython/client/recipe.py
spython/client/shell.py
spython/client/test.py
spython/instance/__init__.py
spython/instance/cmd/__init__.py
spython/instance/cmd/logs.py
spython/instance/cmd/start.py
spython/instance/cmd/stop.py
spython/logger/__init__.py
spython/logger/compatibility.py
spython/logger/message.py
spython/logger/progress.py
spython/logger/spinner.py
spython/main/__init__.py
spython/main/apps.py
spython/main/build.py
spython/main/execute.py
spython/main/export.py
spython/main/help.py
spython/main/inspect.py
spython/main/instances.py
spython/main/pull.py
spython/main/run.py
spython/main/base/Dockerfile
spython/main/base/README.md
spython/main/base/__init__.py
spython/main/base/command.py
spython/main/base/flags.py
spython/main/base/generate.py
spython/main/base/logger.py
spython/main/base/sutils.py
spython/main/parse/__init__.py
spython/main/parse/recipe.py
spython/main/parse/parsers/README.md
spython/main/parse/parsers/__init__.py
spython/main/parse/parsers/base.py
spython/main/parse/parsers/docker.py
spython/main/parse/parsers/singularity.py
spython/main/parse/writers/__init__.py
spython/main/parse/writers/base.py
spython/main/parse/writers/docker.py
spython/main/parse/writers/singularity.py
spython/oci/README.md
spython/oci/__init__.py
spython/oci/config.json
spython/oci/cmd/__init__.py
spython/oci/cmd/actions.py
spython/oci/cmd/mounts.py
spython/oci/cmd/states.py
spython/tests/Xtest_oci.py
spython/tests/__init__.py
spython/tests/conftest.py
spython/tests/helpers.sh
spython/tests/test_base.py
spython/tests/test_client.py
spython/tests/test_client.sh
spython/tests/test_conversion.py
spython/tests/test_instances.py
spython/tests/test_parsers.py
spython/tests/test_recipe.py
spython/tests/test_utils.py
spython/tests/test_writers.py
spython/tests/testdata/Dockerfile
spython/tests/testdata/README.md
spython/tests/testdata/Singularity
spython-0.3.11.dist-info/LICENSE
spython-0.3.11.dist-info/METADATA
spython-0.3.11.dist-info/WHEEL
spython-0.3.11.dist-info/entry_points.txt
spython-0.3.11.dist-info/top_level.txt
spython-0.3.11.dist-info/RECORD
