Metadata-Version: 2.1
Name: spython
Version: 0.3.11
Summary: Command line python tool for working with singularity.
Home-page: https://github.com/singularityhub/singularity-cli
Author: Vanessa Sochat
Author-email: vsoch@users.noreply.github.com
Maintainer: Vanessa Sochat
Maintainer-email: vsoch@users.noreply.github.com
License: LICENSE
Keywords: singularity python client (spython)
Classifier: Intended Audience :: Science/Research
Classifier: Intended Audience :: Developers
Classifier: Programming Language :: Python
Classifier: Topic :: Software Development
Classifier: Topic :: Scientific/Engineering
Classifier: Operating System :: Unix
Classifier: Programming Language :: Python :: 3
License-File: LICENSE
